<?xml version="1.0" encoding="UTF-8"?>

<!-- generated on 2025-03-28 20:34:25 by Eclipse SUMO sumo Version 1.22.0
<sumoConfiguration xmlns:xsi="http://www.w3.org/2001/XMLSchema-instance" xsi:noNamespaceSchemaLocation="http://sumo.dlr.de/xsd/sumoConfiguration.xsd">

    <input>
        <net-file value="/home/cam/Sumo/2025-03-28-20-32-12/osm.net.xml.gz"/>
        <route-files value="/home/cam/Sumo/2025-03-28-20-32-12/trips.trips.xml"/>
        <additional-files value="/home/cam/Sumo/2025-03-28-20-32-12/osm_stops.add.xml"/>
    </input>

    <output>
        <vehroute-output value="/home/cam/Sumo/2025-03-28-20-32-12/vehroutes.xml"/>
        <stop-output value="/home/cam/Sumo/2025-03-28-20-32-12/stopinfos.xml"/>
    </output>

    <time>
        <begin value="0.0"/>
    </time>

    <processing>
        <ignore-route-errors value="true"/>
    </processing>

    <routing>
        <device.rerouting.adaptation-interval value="0"/>
    </routing>

    <report>
        <aggregate-warnings value="5"/>
        <error-log value="/home/cam/Sumo/2025-03-28-20-32-12/trips.trips.xml.errorlog"/>
        <no-step-log value="true"/>
    </report>

</sumoConfiguration>
-->

<stops xmlns:xsi="http://www.w3.org/2001/XMLSchema-instance" xsi:noNamespaceSchemaLocation="http://sumo.dlr.de/xsd/stopinfo_file.xsd">
    <stopinfo id="0_bus_UVX:0" type="pt_bus" lane="1225107993#1_0" pos="16.86" parking="0" started="8.00" ended="38.00" busStop="9932513538" initialPersons="0" loadedPersons="0" unloadedPersons="0" initialContainers="0" loadedContainers="0" unloadedContainers="0"/>
    <stopinfo id="1_bus_UVX:1" type="pt_bus" lane="1225221152#1_0" pos="42.72" parking="0" started="25.00" ended="55.00" busStop="9932488270" initialPersons="0" loadedPersons="0" unloadedPersons="0" initialContainers="0" loadedContainers="0" unloadedContainers="0"/>
    <stopinfo id="2_bus_831:0" type="pt_bus" lane="1225221152#1_0" pos="24.93" parking="0" started="29.00" ended="59.00" busStop="9932488271" initialPersons="0" loadedPersons="0" unloadedPersons="0" initialContainers="0" loadedContainers="0" unloadedContainers="0"/>
    <stopinfo id="3_bus_UVX:2" type="pt_bus" lane="1225107993#1_0" pos="16.86" parking="0" started="47.00" ended="77.00" busStop="9932513538" initialPersons="0" loadedPersons="0" unloadedPersons="0" initialContainers="0" loadedContainers="0" unloadedContainers="0"/>
    <stopinfo id="6_bus_807:0" type="pt_bus" lane="477393514_0" pos="52.47" parking="0" started="69.00" ended="99.00" busStop="9932608366" initialPersons="0" loadedPersons="0" unloadedPersons="0" initialContainers="0" loadedContainers="0" unloadedContainers="0"/>
    <stopinfo id="5_bus_806:0" type="pt_bus" lane="477393511_0" pos="127.28" parking="0" started="74.00" ended="104.00" busStop="9932608367" initialPersons="0" loadedPersons="0" unloadedPersons="0" initialContainers="0" loadedContainers="0" unloadedContainers="0"/>
    <stopinfo id="7_bus_821:0" type="pt_bus" lane="-244437926#0_0" pos="43.27" parking="0" started="104.00" ended="134.00" busStop="-11361052134" initialPersons="0" loadedPersons="0" unloadedPersons="0" initialContainers="0" loadedContainers="0" unloadedContainers="0"/>
    <stopinfo id="8_bus_822:0" type="pt_bus" lane="477393514_0" pos="52.46" parking="0" started="130.00" ended="160.00" busStop="9932608366" initialPersons="0" loadedPersons="0" unloadedPersons="0" initialContainers="0" loadedContainers="0" unloadedContainers="0"/>
    <stopinfo id="9_bus_834:0" type="pt_bus" lane="1095494532#2_0" pos="66.57" parking="0" started="145.00" ended="175.00" busStop="11361153248" initialPersons="0" loadedPersons="0" unloadedPersons="0" initialContainers="0" loadedContainers="0" unloadedContainers="0"/>
    <stopinfo id="11_bus_871:0" type="pt_bus" lane="231250765_0" pos="61.73" parking="0" started="147.00" ended="177.00" busStop="11362282291" initialPersons="0" loadedPersons="0" unloadedPersons="0" initialContainers="0" loadedContainers="0" unloadedContainers="0"/>
    <stopinfo id="10_bus_862:0" type="pt_bus" lane="776681829#5_0" pos="99.14" parking="0" started="150.00" ended="180.00" busStop="6863882459" initialPersons="0" loadedPersons="0" unloadedPersons="0" initialContainers="0" loadedContainers="0" unloadedContainers="0"/>
    <stopinfo id="0_bus_UVX:0" type="pt_bus" lane="1001934331#3_0" pos="27.80" parking="0" started="150.00" ended="180.00" busStop="9247517723" initialPersons="0" loadedPersons="0" unloadedPersons="0" initialContainers="0" loadedContainers="0" unloadedContainers="0"/>
    <stopinfo id="3_bus_UVX:2" type="pt_bus" lane="1072819409#3_0" pos="10.00" parking="0" started="193.00" ended="223.00" busStop="9932608364" initialPersons="0" loadedPersons="0" unloadedPersons="0" initialContainers="0" loadedContainers="0" unloadedContainers="0"/>
    <stopinfo id="14_bus_880:1" type="pt_bus" lane="1227169322#1_0" pos="12.57" parking="0" started="207.00" ended="237.00" busStop="10218747078@16719450" initialPersons="0" loadedPersons="0" unloadedPersons="0" initialContainers="0" loadedContainers="0" unloadedContainers="0"/>
    <stopinfo id="13_bus_880:0" type="pt_bus" lane="776681829#5_0" pos="99.12" parking="0" started="217.00" ended="247.00" busStop="6863882459" initialPersons="0" loadedPersons="0" unloadedPersons="0" initialContainers="0" loadedContainers="0" unloadedContainers="0"/>
    <stopinfo id="1_bus_UVX:1" type="pt_bus" lane="477393514_0" pos="52.46" parking="0" started="244.00" ended="274.00" busStop="9932608366" initialPersons="0" loadedPersons="0" unloadedPersons="0" initialContainers="0" loadedContainers="0" unloadedContainers="0"/>
    <stopinfo id="4_bus_805:0" type="pt_bus" lane="1225096172#3_0" pos="35.19" parking="0" started="275.00" ended="305.00" busStop="8584737276" initialPersons="0" loadedPersons="0" unloadedPersons="0" initialContainers="0" loadedContainers="0" unloadedContainers="0"/>
    <stopinfo id="15_bus_850:0" type="pt_bus" lane="1224483160_0" pos="101.69" parking="0" started="277.00" ended="307.00" busStop="9932513543" initialPersons="0" loadedPersons="0" unloadedPersons="0" initialContainers="0" loadedContainers="0" unloadedContainers="0"/>
    <stopinfo id="0_bus_UVX:0" type="pt_bus" lane="1001934331#10_0" pos="125.67" parking="0" started="302.00" ended="332.00" busStop="605205962" initialPersons="0" loadedPersons="0" unloadedPersons="0" initialContainers="0" loadedContainers="0" unloadedContainers="0"/>
    <stopinfo id="16_bus_850:1" type="pt_bus" lane="231250765_0" pos="82.41" parking="0" started="322.00" ended="352.00" busStop="11360306139" initialPersons="0" loadedPersons="0" unloadedPersons="0" initialContainers="0" loadedContainers="0" unloadedContainers="0"/>
    <stopinfo id="3_bus_UVX:2" type="pt_bus" lane="10247300#3_0" pos="135.70" parking="0" started="322.00" ended="352.00" busStop="9932608360" initialPersons="0" loadedPersons="0" unloadedPersons="0" initialContainers="0" loadedContainers="0" unloadedContainers="0"/>
    <stopinfo id="12_bus_871:1" type="pt_bus" lane="231250765_0" pos="61.72" parking="0" started="324.00" ended="354.00" busStop="11362282291" initialPersons="0" loadedPersons="0" unloadedPersons="0" initialContainers="0" loadedContainers="0" unloadedContainers="0"/>
    <stopinfo id="17_bus_862:1" type="pt_bus" lane="463704557#1_0" pos="112.34" parking="0" started="352.00" ended="382.00" busStop="9932488272" initialPersons="0" loadedPersons="0" unloadedPersons="0" initialContainers="0" loadedContainers="0" unloadedContainers="0"/>
    <stopinfo id="2_bus_831:0" type="pt_bus" lane="346646696#0_0" pos="25.48" parking="0" started="371.00" ended="401.00" busStop="8927848924" initialPersons="0" loadedPersons="0" unloadedPersons="0" initialContainers="0" loadedContainers="0" unloadedContainers="0"/>
    <stopinfo id="19_train_750:0" type="pt_train" lane="297896758_0" pos="200.00" parking="0" started="387.00" ended="417.00" busStop="6593866724" initialPersons="0" loadedPersons="0" unloadedPersons="0" initialContainers="0" loadedContainers="0" unloadedContainers="0"/>
    <stopinfo id="18_bus_807:1" type="pt_bus" lane="231250765_0" pos="182.79" parking="0" started="392.00" ended="422.00" busStop="11357516426" initialPersons="0" loadedPersons="0" unloadedPersons="0" initialContainers="0" loadedContainers="0" unloadedContainers="0"/>
    <stopinfo id="1_bus_UVX:1" type="pt_bus" lane="882705687#1_0" pos="32.97" parking="0" started="395.00" ended="425.00" busStop="8881604599" initialPersons="0" loadedPersons="0" unloadedPersons="0" initialContainers="0" loadedContainers="0" unloadedContainers="0"/>
    <stopinfo id="21_bus_833:0" type="pt_bus" lane="684673673#1_0" pos="112.80" parking="0" started="414.00" ended="444.00" busStop="9932513540" initialPersons="0" loadedPersons="0" unloadedPersons="0" initialContainers="0" loadedContainers="0" unloadedContainers="0"/>
    <stopinfo id="15_bus_850:0" type="pt_bus" lane="-749991160_0" pos="0.18" parking="0" started="415.00" ended="445.00" busStop="-8886452609" initialPersons="0" loadedPersons="0" unloadedPersons="0" initialContainers="0" loadedContainers="0" unloadedContainers="0"/>
    <stopinfo id="22_bus_831:1" type="pt_bus" lane="1224483160_0" pos="64.57" parking="0" started="423.00" ended="453.00" busStop="2396515835" initialPersons="0" loadedPersons="0" unloadedPersons="0" initialContainers="0" loadedContainers="0" unloadedContainers="0"/>
    <stopinfo id="3_bus_UVX:2" type="pt_bus" lane="684673720#3_0" pos="87.45" parking="0" started="436.00" ended="466.00" busStop="9932608361" initialPersons="0" loadedPersons="0" unloadedPersons="0" initialContainers="0" loadedContainers="0" unloadedContainers="0"/>
    <stopinfo id="17_bus_862:1" type="pt_bus" lane="-262148878#2_0" pos="26.58" parking="0" started="449.00" ended="479.00" busStop="-8544776077" initialPersons="0" loadedPersons="0" unloadedPersons="0" initialContainers="0" loadedContainers="0" unloadedContainers="0"/>
    <stopinfo id="2_bus_831:0" type="pt_bus" lane="477393511_0" pos="127.28" parking="0" started="486.00" ended="516.00" busStop="9932608367" initialPersons="0" loadedPersons="0" unloadedPersons="0" initialContainers="0" loadedContainers="0" unloadedContainers="0"/>
    <stopinfo id="0_bus_UVX:0" type="pt_bus" lane="1028565365#7_0" pos="107.96" parking="0" started="487.00" ended="517.00" busStop="6321664858" initialPersons="0" loadedPersons="0" unloadedPersons="0" initialContainers="0" loadedContainers="0" unloadedContainers="0"/>
    <stopinfo id="24_train_California_Zephyr:1" type="pt_train" lane="298119461#9_0" pos="385.13" parking="0" started="490.00" ended="520.00" busStop="3020208745" initialPersons="0" loadedPersons="0" unloadedPersons="0" initialContainers="0" loadedContainers="0" unloadedContainers="0"/>
    <stopinfo id="15_bus_850:0" type="pt_bus" lane="1001934332#0_0" pos="0.20" parking="0" started="498.00" ended="528.00" busStop="9103874877" initialPersons="0" loadedPersons="0" unloadedPersons="0" initialContainers="0" loadedContainers="0" unloadedContainers="0"/>
    <stopinfo id="20_bus_806:1" type="pt_bus" lane="346479769#1_0" pos="25.90" parking="0" started="511.00" ended="541.00" busStop="8577326192" initialPersons="0" loadedPersons="0" unloadedPersons="0" initialContainers="0" loadedContainers="0" unloadedContainers="0"/>
    <stopinfo id="17_bus_862:1" type="pt_bus" lane="-1210607046#0_0" pos="31.24" parking="0" started="515.00" ended="545.00" busStop="-9128347751" initialPersons="0" loadedPersons="0" unloadedPersons="0" initialContainers="0" loadedContainers="0" unloadedContainers="0"/>
    <stopinfo id="27_bus_805:1" type="pt_bus" lane="477393511_0" pos="127.28" parking="0" started="523.00" ended="553.00" busStop="9932608367" initialPersons="0" loadedPersons="0" unloadedPersons="0" initialContainers="0" loadedContainers="0" unloadedContainers="0"/>
    <stopinfo id="21_bus_833:0" type="pt_bus" lane="60747906#5_0" pos="15.00" parking="0" started="525.00" ended="555.00" busStop="8663447666" initialPersons="0" loadedPersons="0" unloadedPersons="0" initialContainers="0" loadedContainers="0" unloadedContainers="0"/>
    <stopinfo id="28_bus_834:1" type="pt_bus" lane="684673673#1_0" pos="131.62" parking="0" started="537.00" ended="567.00" busStop="5388433608" initialPersons="0" loadedPersons="0" unloadedPersons="0" initialContainers="0" loadedContainers="0" unloadedContainers="0"/>
    <stopinfo id="26_train_Heber_Valley_Railroad:0" type="pt_train" lane="216231337#1_0" pos="132.89" parking="0" started="539.00" ended="569.00" busStop="12359994676" initialPersons="0" loadedPersons="0" unloadedPersons="0" initialContainers="0" loadedContainers="0" unloadedContainers="0"/>
    <stopinfo id="1_bus_UVX:1" type="pt_bus" lane="1001619396#1_0" pos="24.42" parking="0" started="539.00" ended="569.00" busStop="6863882533" initialPersons="0" loadedPersons="0" unloadedPersons="0" initialContainers="0" loadedContainers="0" unloadedContainers="0"/>
    <stopinfo id="14_bus_880:1" type="pt_bus" lane="10244417#2_0" pos="33.60" parking="0" started="541.00" ended="571.00" busStop="8781455725" initialPersons="0" loadedPersons="0" unloadedPersons="0" initialContainers="0" loadedContainers="0" unloadedContainers="0"/>
    <stopinfo id="29_bus_822:1" type="pt_bus" lane="-244437926#0_0" pos="43.26" parking="0" started="544.00" ended="574.00" busStop="-11361052134" initialPersons="0" loadedPersons="0" unloadedPersons="0" initialContainers="0" loadedContainers="0" unloadedContainers="0"/>
    <stopinfo id="17_bus_862:1" type="pt_bus" lane="-413212997#4_0" pos="64.93" parking="0" started="567.00" ended="597.00" busStop="-9124943047" initialPersons="0" loadedPersons="0" unloadedPersons="0" initialContainers="0" loadedContainers="0" unloadedContainers="0"/>
    <stopinfo id="15_bus_850:0" type="pt_bus" lane="845552832#1_0" pos="34.14" parking="0" started="573.00" ended="603.00" busStop="8542915352" initialPersons="0" loadedPersons="0" unloadedPersons="0" initialContainers="0" loadedContainers="0" unloadedContainers="0"/>
    <stopinfo id="21_bus_833:0" type="pt_bus" lane="-1081151280#7_0" pos="24.91" parking="0" started="590.00" ended="620.00" busStop="-8849269922" initialPersons="0" loadedPersons="0" unloadedPersons="0" initialContainers="0" loadedContainers="0" unloadedContainers="0"/>
    <stopinfo id="30_bus_821:1" type="pt_bus" lane="1224483160_0" pos="83.96" parking="0" started="593.00" ended="623.00" busStop="9932513542" initialPersons="0" loadedPersons="0" unloadedPersons="0" initialContainers="0" loadedContainers="0" unloadedContainers="0"/>
    <stopinfo id="0_bus_UVX:0" type="pt_bus" lane="1028565365#14_0" pos="120.38" parking="0" started="607.00" ended="637.00" busStop="9932608368" initialPersons="0" loadedPersons="0" unloadedPersons="0" initialContainers="0" loadedContainers="0" unloadedContainers="0"/>
    <stopinfo id="3_bus_UVX:2" type="pt_bus" lane="887681418#1_0" pos="19.10" parking="0" started="616.00" ended="646.00" busStop="9932608365" initialPersons="0" loadedPersons="0" unloadedPersons="0" initialContainers="0" loadedContainers="0" unloadedContainers="0"/>
    <stopinfo id="20_bus_806:1" type="pt_bus" lane="231250765_0" pos="165.48" parking="0" started="653.00" ended="683.00" busStop="8577296199" initialPersons="0" loadedPersons="0" unloadedPersons="0" initialContainers="0" loadedContainers="0" unloadedContainers="0"/>
    <stopinfo id="17_bus_862:1" type="pt_bus" lane="1095496457_0" pos="30.08" parking="0" started="671.00" ended="701.00" busStop="8692170671" initialPersons="0" loadedPersons="0" unloadedPersons="0" initialContainers="0" loadedContainers="0" unloadedContainers="0"/>
    <stopinfo id="15_bus_850:0" type="pt_bus" lane="845552832#7_0" pos="31.79" parking="0" started="673.00" ended="703.00" busStop="8783771089" initialPersons="0" loadedPersons="0" unloadedPersons="0" initialContainers="0" loadedContainers="0" unloadedContainers="0"/>
    <stopinfo id="1_bus_UVX:1" type="pt_bus" lane="1036897385#1_0" pos="402.54" parking="0" started="682.00" ended="712.00" busStop="6863882534" initialPersons="0" loadedPersons="0" unloadedPersons="0" initialContainers="0" loadedContainers="0" unloadedContainers="0"/>
    <stopinfo id="10_bus_862:0" type="pt_bus" lane="463704557#1_0" pos="112.34" parking="0" started="692.00" ended="722.00" busStop="9932488272" initialPersons="0" loadedPersons="0" unloadedPersons="0" initialContainers="0" loadedContainers="0" unloadedContainers="0"/>
    <stopinfo id="21_bus_833:0" type="pt_bus" lane="-10231591#8_0" pos="41.98" parking="0" started="698.00" ended="728.00" busStop="-9118090936" initialPersons="0" loadedPersons="0" unloadedPersons="0" initialContainers="0" loadedContainers="0" unloadedContainers="0"/>
    <stopinfo id="2_bus_831:0" type="pt_bus" lane="-229097623#11_0" pos="47.89" parking="0" started="702.00" ended="732.00" busStop="-8720294827" initialPersons="0" loadedPersons="0" unloadedPersons="0" initialContainers="0" loadedContainers="0" unloadedContainers="0"/>
    <stopinfo id="19_train_750:0" type="pt_train" lane="-297896760#1_0" pos="165.39" parking="0" started="723.00" ended="753.00" busStop="-7123084666" initialPersons="0" loadedPersons="0" unloadedPersons="0" initialContainers="0" loadedContainers="0" unloadedContainers="0"/>
    <stopinfo id="13_bus_880:0" type="pt_bus" lane="10244417#2_0" pos="33.62" parking="0" started="725.00" ended="755.00" busStop="8781455725" initialPersons="0" loadedPersons="0" unloadedPersons="0" initialContainers="0" loadedContainers="0" unloadedContainers="0"/>
    <stopinfo id="21_bus_833:0" type="pt_bus" lane="673875825#1_0" pos="56.31" parking="0" started="770.00" ended="800.00" busStop="8783754381" initialPersons="0" loadedPersons="0" unloadedPersons="0" initialContainers="0" loadedContainers="0" unloadedContainers="0"/>
    <stopinfo id="3_bus_UVX:2" type="pt_bus" lane="1225107993#1_0" pos="16.86" parking="0" started="802.00" ended="832.00" busStop="9932513538" initialPersons="0" loadedPersons="0" unloadedPersons="0" initialContainers="0" loadedContainers="0" unloadedContainers="0"/>
    <stopinfo id="17_bus_862:1" type="pt_bus" lane="477393514_0" pos="52.46" parking="0" started="805.00" ended="835.00" busStop="9932608366" initialPersons="0" loadedPersons="0" unloadedPersons="0" initialContainers="0" loadedContainers="0" unloadedContainers="0"/>
    <stopinfo id="15_bus_850:0" type="pt_bus" lane="10233539#1_0" pos="30.94" parking="0" started="818.00" ended="848.00" busStop="8869089876" initialPersons="0" loadedPersons="0" unloadedPersons="0" initialContainers="0" loadedContainers="0" unloadedContainers="0"/>
    <stopinfo id="0_bus_UVX:0" type="pt_bus" lane="1001848378#10_0" pos="19.77" parking="0" started="831.00" ended="861.00" busStop="5924331785" initialPersons="0" loadedPersons="0" unloadedPersons="0" initialContainers="0" loadedContainers="0" unloadedContainers="0"/>
    <stopinfo id="21_bus_833:0" type="pt_bus" lane="1192673079#1_0" pos="26.05" parking="0" started="843.00" ended="873.00" busStop="9118850498" initialPersons="0" loadedPersons="0" unloadedPersons="0" initialContainers="0" loadedContainers="0" unloadedContainers="0"/>
    <stopinfo id="17_bus_862:1" type="pt_bus" lane="-10242245#6_0" pos="42.33" parking="0" started="896.00" ended="926.00" busStop="-8929834914" initialPersons="0" loadedPersons="0" unloadedPersons="0" initialContainers="0" loadedContainers="0" unloadedContainers="0"/>
    <stopinfo id="15_bus_850:0" type="pt_bus" lane="10233539#16_0" pos="34.39" parking="0" started="914.00" ended="944.00" busStop="8790811499" initialPersons="0" loadedPersons="0" unloadedPersons="0" initialContainers="0" loadedContainers="0" unloadedContainers="0"/>
    <stopinfo id="21_bus_833:0" type="pt_bus" lane="1192673080#1_0" pos="55.41" parking="0" started="935.00" ended="965.00" busStop="8570320809" initialPersons="0" loadedPersons="0" unloadedPersons="0" initialContainers="0" loadedContainers="0" unloadedContainers="0"/>
    <stopinfo id="0_bus_UVX:0" type="pt_bus" lane="1001845740#0_0" pos="56.19" parking="0" started="935.00" ended="965.00" busStop="9932608374" initialPersons="0" loadedPersons="0" unloadedPersons="0" initialContainers="0" loadedContainers="0" unloadedContainers="0"/>
    <stopinfo id="17_bus_862:1" type="pt_bus" lane="-346646696#0_0" pos="28.09" parking="0" started="973.00" ended="1003.00" busStop="-8542423137" initialPersons="0" loadedPersons="0" unloadedPersons="0" initialContainers="0" loadedContainers="0" unloadedContainers="0"/>
    <stopinfo id="15_bus_850:0" type="pt_bus" lane="1195524524#3_0" pos="13.67" parking="0" started="983.00" ended="1013.00" busStop="11493019591" initialPersons="0" loadedPersons="0" unloadedPersons="0" initialContainers="0" loadedContainers="0" unloadedContainers="0"/>
    <stopinfo id="1_bus_UVX:1" type="pt_bus" lane="1001839206#16_0" pos="28.92" parking="0" started="995.00" ended="1025.00" busStop="6324411420" initialPersons="0" loadedPersons="0" unloadedPersons="0" initialContainers="0" loadedContainers="0" unloadedContainers="0"/>
    <stopinfo id="14_bus_880:1" type="pt_bus" lane="776681829#5_0" pos="99.15" parking="0" started="1018.00" ended="1048.00" busStop="6863882459" initialPersons="0" loadedPersons="0" unloadedPersons="0" initialContainers="0" loadedContainers="0" unloadedContainers="0"/>
    <stopinfo id="4_bus_805:0" type="pt_bus" lane="1037870374#1_0" pos="22.22" parking="0" started="1040.00" ended="1070.00" busStop="8552049555" initialPersons="0" loadedPersons="0" unloadedPersons="0" initialContainers="0" loadedContainers="0" unloadedContainers="0"/>
    <stopinfo id="15_bus_850:0" type="pt_bus" lane="1195524525#3_0" pos="62.22" parking="0" started="1043.00" ended="1073.00" busStop="8925359570" initialPersons="0" loadedPersons="0" unloadedPersons="0" initialContainers="0" loadedContainers="0" unloadedContainers="0"/>
    <stopinfo id="17_bus_862:1" type="pt_bus" lane="346646690#2_0" pos="23.09" parking="0" started="1051.00" ended="1081.00" busStop="8895668833" initialPersons="0" loadedPersons="0" unloadedPersons="0" initialContainers="0" loadedContainers="0" unloadedContainers="0"/>
    <stopinfo id="13_bus_880:0" type="pt_bus" lane="1227169322#1_0" pos="12.60" parking="0" started="1069.00" ended="1099.00" busStop="10218747078" initialPersons="0" loadedPersons="0" unloadedPersons="0" initialContainers="0" loadedContainers="0" unloadedContainers="0"/>
    <stopinfo id="5_bus_806:0" type="pt_bus" lane="346479769#1_0" pos="25.92" parking="0" started="1094.00" ended="1124.00" busStop="8577326192" initialPersons="0" loadedPersons="0" unloadedPersons="0" initialContainers="0" loadedContainers="0" unloadedContainers="0"/>
    <stopinfo id="29_bus_822:1" type="pt_bus" lane="933026951_0" pos="37.97" parking="0" started="1098.00" ended="1128.00" busStop="8849397580" initialPersons="0" loadedPersons="0" unloadedPersons="0" initialContainers="0" loadedContainers="0" unloadedContainers="0"/>
    <stopinfo id="2_bus_831:0" type="pt_bus" lane="-1030777448#5_0" pos="30.68" parking="0" started="1104.00" ended="1134.00" busStop="-8925330146" initialPersons="0" loadedPersons="0" unloadedPersons="0" initialContainers="0" loadedContainers="0" unloadedContainers="0"/>
    <stopinfo id="15_bus_850:0" type="pt_bus" lane="816689128#1_0" pos="43.40" parking="0" started="1104.00" ended="1134.00" busStop="11493019590" initialPersons="0" loadedPersons="0" unloadedPersons="0" initialContainers="0" loadedContainers="0" unloadedContainers="0"/>
    <stopinfo id="21_bus_833:0" type="pt_bus" lane="228562182#3_0" pos="97.34" parking="0" started="1111.00" ended="1141.00" busStop="8568314382" initialPersons="0" loadedPersons="0" unloadedPersons="0" initialContainers="0" loadedContainers="0" unloadedContainers="0"/>
    <stopinfo id="17_bus_862:1" type="pt_bus" lane="541635286#1_0" pos="27.17" parking="0" started="1112.00" ended="1142.00" busStop="8921201186" initialPersons="0" loadedPersons="0" unloadedPersons="0" initialContainers="0" loadedContainers="0" unloadedContainers="0"/>
    <stopinfo id="0_bus_UVX:0" type="pt_bus" lane="-36322646#4_0" pos="32.54" parking="0" started="1164.00" ended="1194.00" busStop="-9932608377" initialPersons="0" loadedPersons="0" unloadedPersons="0" initialContainers="0" loadedContainers="0" unloadedContainers="0"/>
    <stopinfo id="25_train_750:1" type="pt_train" lane="709757177_0" pos="327.84" parking="0" started="1164.00" ended="1194.00" busStop="6341264443" initialPersons="0" loadedPersons="0" unloadedPersons="0" initialContainers="0" loadedContainers="0" unloadedContainers="0"/>
    <stopinfo id="19_train_750:0" type="pt_train" lane="-298119547#2_0" pos="262.26" parking="0" started="1167.00" ended="1197.00" busStop="-3020209235" initialPersons="0" loadedPersons="0" unloadedPersons="0" initialContainers="0" loadedContainers="0" unloadedContainers="0"/>
    <stopinfo id="17_bus_862:1" type="pt_bus" lane="566551616#1_0" pos="19.80" parking="0" started="1180.00" ended="1210.00" busStop="8878017584" initialPersons="0" loadedPersons="0" unloadedPersons="0" initialContainers="0" loadedContainers="0" unloadedContainers="0"/>
    <stopinfo id="22_bus_831:1" type="pt_bus" lane="-10246981#0_0" pos="43.23" parking="0" started="1186.00" ended="1216.00" busStop="-8669789982" initialPersons="0" loadedPersons="0" unloadedPersons="0" initialContainers="0" loadedContainers="0" unloadedContainers="0"/>
    <stopinfo id="15_bus_850:0" type="pt_bus" lane="231243105#15_0" pos="12.47" parking="0" started="1193.00" ended="1223.00" busStop="8672436476" initialPersons="0" loadedPersons="0" unloadedPersons="0" initialContainers="0" loadedContainers="0" unloadedContainers="0"/>
    <stopinfo id="21_bus_833:0" type="pt_bus" lane="157871255#2_0" pos="27.77" parking="0" started="1193.00" ended="1223.00" busStop="8692173276" initialPersons="0" loadedPersons="0" unloadedPersons="0" initialContainers="0" loadedContainers="0" unloadedContainers="0"/>
    <stopinfo id="6_bus_807:0" type="pt_bus" lane="231250765_0" pos="182.82" parking="0" started="1206.00" ended="1236.00" busStop="11357516426" initialPersons="0" loadedPersons="0" unloadedPersons="0" initialContainers="0" loadedContainers="0" unloadedContainers="0"/>
    <stopinfo id="2_bus_831:0" type="pt_bus" lane="346673260#3_0" pos="14.99" parking="0" started="1228.00" ended="1258.00" busStop="6324127515" initialPersons="0" loadedPersons="0" unloadedPersons="0" initialContainers="0" loadedContainers="0" unloadedContainers="0"/>
    <stopinfo id="5_bus_806:0" type="pt_bus" lane="231250765_0" pos="165.48" parking="0" started="1237.00" ended="1267.00" busStop="8577296199" initialPersons="0" loadedPersons="0" unloadedPersons="0" initialContainers="0" loadedContainers="0" unloadedContainers="0"/>
    <stopinfo id="17_bus_862:1" type="pt_bus" lane="566551615#2_0" pos="13.20" parking="0" started="1242.00" ended="1272.00" busStop="366499661" initialPersons="0" loadedPersons="0" unloadedPersons="0" initialContainers="0" loadedContainers="0" unloadedContainers="0"/>
    <stopinfo id="0_bus_UVX:0" type="pt_bus" lane="36322642#1_0" pos="124.63" parking="0" started="1245.00" ended="1275.00" busStop="423696141" initialPersons="0" loadedPersons="0" unloadedPersons="0" initialContainers="0" loadedContainers="0" unloadedContainers="0"/>
    <stopinfo id="15_bus_850:0" type="pt_bus" lane="231243105#21_0" pos="30.46" parking="0" started="1262.00" ended="1292.00" busStop="8929705824" initialPersons="0" loadedPersons="0" unloadedPersons="0" initialContainers="0" loadedContainers="0" unloadedContainers="0"/>
    <stopinfo id="9_bus_834:0" type="pt_bus" lane="684673673#1_0" pos="27.90" parking="0" started="1266.00" ended="1296.00" busStop="9932513537" initialPersons="0" loadedPersons="0" unloadedPersons="0" initialContainers="0" loadedContainers="0" unloadedContainers="0"/>
    <stopinfo id="1_bus_UVX:1" type="pt_bus" lane="1029175182#1_0" pos="30.67" parking="0" started="1285.00" ended="1315.00" busStop="423696136" initialPersons="0" loadedPersons="0" unloadedPersons="0" initialContainers="0" loadedContainers="0" unloadedContainers="0"/>
    <stopinfo id="17_bus_862:1" type="pt_bus" lane="566551615#4_0" pos="42.00" parking="0" started="1295.00" ended="1325.00" busStop="9124954631" initialPersons="0" loadedPersons="0" unloadedPersons="0" initialContainers="0" loadedContainers="0" unloadedContainers="0"/>
    <stopinfo id="21_bus_833:0" type="pt_bus" lane="1225108307#5_0" pos="18.96" parking="0" started="1313.00" ended="1343.00" busStop="8542953438" initialPersons="0" loadedPersons="0" unloadedPersons="0" initialContainers="0" loadedContainers="0" unloadedContainers="0"/>
    <stopinfo id="15_bus_850:0" type="pt_bus" lane="231243105#26_0" pos="24.54" parking="0" started="1316.00" ended="1346.00" busStop="8921183207" initialPersons="0" loadedPersons="0" unloadedPersons="0" initialContainers="0" loadedContainers="0" unloadedContainers="0"/>
    <stopinfo id="22_bus_831:1" type="pt_bus" lane="742968416#1_0" pos="25.43" parking="0" started="1361.00" ended="1391.00" busStop="8544798609" initialPersons="0" loadedPersons="0" unloadedPersons="0" initialContainers="0" loadedContainers="0" unloadedContainers="0"/>
    <stopinfo id="1_bus_UVX:1" type="pt_bus" lane="36322646#4_0" pos="61.22" parking="0" started="1366.00" ended="1396.00" busStop="9932608376" initialPersons="0" loadedPersons="0" unloadedPersons="0" initialContainers="0" loadedContainers="0" unloadedContainers="0"/>
    <stopinfo id="7_bus_821:0" type="pt_bus" lane="1224483160_0" pos="83.95" parking="0" started="1373.00" ended="1403.00" busStop="9932513542" initialPersons="0" loadedPersons="0" unloadedPersons="0" initialContainers="0" loadedContainers="0" unloadedContainers="0"/>
    <stopinfo id="17_bus_862:1" type="pt_bus" lane="28474650#4_0" pos="17.20" parking="0" started="1380.00" ended="1410.00" busStop="9123289593" initialPersons="0" loadedPersons="0" unloadedPersons="0" initialContainers="0" loadedContainers="0" unloadedContainers="0"/>
    <stopinfo id="15_bus_850:0" type="pt_bus" lane="1029191646#1_0" pos="31.69" parking="0" started="1401.00" ended="1431.00" busStop="8849280836" initialPersons="0" loadedPersons="0" unloadedPersons="0" initialContainers="0" loadedContainers="0" unloadedContainers="0"/>
    <stopinfo id="2_bus_831:0" type="pt_bus" lane="-932976231#1_0" pos="15.00" parking="0" started="1454.00" ended="1484.00" busStop="-8849380348" initialPersons="0" loadedPersons="0" unloadedPersons="0" initialContainers="0" loadedContainers="0" unloadedContainers="0"/>
    <stopinfo id="17_bus_862:1" type="pt_bus" lane="28474650#14_0" pos="28.04" parking="0" started="1455.00" ended="1485.00" busStop="9124338579" initialPersons="0" loadedPersons="0" unloadedPersons="0" initialContainers="0" loadedContainers="0" unloadedContainers="0"/>
    <stopinfo id="21_bus_833:0" type="pt_bus" lane="1031006750#11_0" pos="58.05" parking="0" started="1467.00" ended="1497.00" busStop="9123295956" initialPersons="0" loadedPersons="0" unloadedPersons="0" initialContainers="0" loadedContainers="0" unloadedContainers="0"/>
    <stopinfo id="22_bus_831:1" type="pt_bus" lane="932976230#0_0" pos="15.00" parking="0" started="1471.00" ended="1501.00" busStop="8990592930" initialPersons="0" loadedPersons="0" unloadedPersons="0" initialContainers="0" loadedContainers="0" unloadedContainers="0"/>
    <stopinfo id="15_bus_850:0" type="pt_bus" lane="31838249#5_0" pos="30.05" parking="0" started="1483.00" ended="1513.00" busStop="8895635104" initialPersons="0" loadedPersons="0" unloadedPersons="0" initialContainers="0" loadedContainers="0" unloadedContainers="0"/>
    <stopinfo id="19_train_750:0" type="pt_train" lane="-298119477#5_0" pos="185.28" parking="0" started="1493.00" ended="1523.00" busStop="-6341264446" initialPersons="0" loadedPersons="0" unloadedPersons="0" initialContainers="0" loadedContainers="0" unloadedContainers="0"/>
    <stopinfo id="25_train_750:1" type="pt_train" lane="762329402#5_0" pos="2746.35" parking="0" started="1494.00" ended="1524.00" busStop="3020209244" initialPersons="0" loadedPersons="0" unloadedPersons="0" initialContainers="0" loadedContainers="0" unloadedContainers="0"/>
    <stopinfo id="18_bus_807:1" type="pt_bus" lane="477393511_0" pos="127.28" parking="0" started="1511.00" ended="1541.00" busStop="9932608367" initialPersons="0" loadedPersons="0" unloadedPersons="0" initialContainers="0" loadedContainers="0" unloadedContainers="0"/>
    <stopinfo id="27_bus_805:1" type="pt_bus" lane="1225107993#1_0" pos="24.39" parking="0" started="1520.00" ended="1550.00" busStop="5388433609" initialPersons="0" loadedPersons="0" unloadedPersons="0" initialContainers="0" loadedContainers="0" unloadedContainers="0"/>
    <stopinfo id="0_bus_UVX:0" type="pt_bus" lane="1001839202#3_0" pos="688.55" parking="0" started="1530.00" ended="1560.00" busStop="9932608383" initialPersons="0" loadedPersons="0" unloadedPersons="0" initialContainers="0" loadedContainers="0" unloadedContainers="0"/>
    <stopinfo id="17_bus_862:1" type="pt_bus" lane="45877227#6_0" pos="18.66" parking="0" started="1531.00" ended="1561.00" busStop="8921196947" initialPersons="0" loadedPersons="0" unloadedPersons="0" initialContainers="0" loadedContainers="0" unloadedContainers="0"/>
    <stopinfo id="15_bus_850:0" type="pt_bus" lane="31838249#18_0" pos="14.98" parking="0" started="1545.00" ended="1575.00" busStop="8561017088" initialPersons="0" loadedPersons="0" unloadedPersons="0" initialContainers="0" loadedContainers="0" unloadedContainers="0"/>
    <stopinfo id="8_bus_822:0" type="pt_bus" lane="-244437926#0_0" pos="43.27" parking="0" started="1558.00" ended="1588.00" busStop="-11361052134" initialPersons="0" loadedPersons="0" unloadedPersons="0" initialContainers="0" loadedContainers="0" unloadedContainers="0"/>
    <stopinfo id="21_bus_833:0" type="pt_bus" lane="1087202049#7_0" pos="27.79" parking="0" started="1567.00" ended="1597.00" busStop="11463381201" initialPersons="0" loadedPersons="0" unloadedPersons="0" initialContainers="0" loadedContainers="0" unloadedContainers="0"/>
    <stopinfo id="22_bus_831:1" type="pt_bus" lane="932976227#0_0" pos="18.98" parking="0" started="1571.00" ended="1601.00" busStop="8663648301" initialPersons="0" loadedPersons="0" unloadedPersons="0" initialContainers="0" loadedContainers="0" unloadedContainers="0"/>
    <stopinfo id="28_bus_834:1" type="pt_bus" lane="1095494532#2_0" pos="66.56" parking="0" started="1580.00" ended="1610.00" busStop="11361153248@9499501" initialPersons="0" loadedPersons="0" unloadedPersons="0" initialContainers="0" loadedContainers="0" unloadedContainers="0"/>
    <stopinfo id="17_bus_862:1" type="pt_bus" lane="1237615511#2_0" pos="30.17" parking="0" started="1623.00" ended="1653.00" busStop="957769101" initialPersons="0" loadedPersons="0" unloadedPersons="0" initialContainers="0" loadedContainers="0" unloadedContainers="0"/>
    <stopinfo id="15_bus_850:0" type="pt_bus" lane="31838249#23_0" pos="21.26" parking="0" started="1625.00" ended="1655.00" busStop="8781411676" initialPersons="0" loadedPersons="0" unloadedPersons="0" initialContainers="0" loadedContainers="0" unloadedContainers="0"/>
    <stopinfo id="2_bus_831:0" type="pt_bus" lane="742968415#1_0" pos="22.48" parking="0" started="1640.00" ended="1670.00" busStop="8886481767" initialPersons="0" loadedPersons="0" unloadedPersons="0" initialContainers="0" loadedContainers="0" unloadedContainers="0"/>
    <stopinfo id="23_train_California_Zephyr:0" type="pt_train" lane="298119461#9_0" pos="385.13" parking="0" started="1652.00" ended="1682.00" busStop="3020208745" initialPersons="0" loadedPersons="0" unloadedPersons="0" initialContainers="0" loadedContainers="0" unloadedContainers="0"/>
    <stopinfo id="1_bus_UVX:1" type="pt_bus" lane="1001845739#1_0" pos="30.63" parking="0" started="1655.00" ended="1685.00" busStop="9932608375" initialPersons="0" loadedPersons="0" unloadedPersons="0" initialContainers="0" loadedContainers="0" unloadedContainers="0"/>
    <stopinfo id="15_bus_850:0" type="pt_bus" lane="31838249#29_0" pos="67.16" parking="0" started="1681.00" ended="1711.00" busStop="8784064050" initialPersons="0" loadedPersons="0" unloadedPersons="0" initialContainers="0" loadedContainers="0" unloadedContainers="0"/>
    <stopinfo id="27_bus_805:1" type="pt_bus" lane="-117922059#4_0" pos="30.29" parking="0" started="1687.00" ended="1717.00" busStop="-9138268649" initialPersons="0" loadedPersons="0" unloadedPersons="0" initialContainers="0" loadedContainers="0" unloadedContainers="0"/>
    <stopinfo id="4_bus_805:0" type="pt_bus" lane="-533097177#0_0" pos="35.29" parking="0" started="1695.00" ended="1725.00" busStop="-8551597362" initialPersons="0" loadedPersons="0" unloadedPersons="0" initialContainers="0" loadedContainers="0" unloadedContainers="0"/>
    <stopinfo id="17_bus_862:1" type="pt_bus" lane="1237615510#12_0" pos="17.17" parking="0" started="1698.00" ended="1728.00" busStop="957772651" initialPersons="0" loadedPersons="0" unloadedPersons="0" initialContainers="0" loadedContainers="0" unloadedContainers="0"/>
    <stopinfo id="20_bus_806:1" type="pt_bus" lane="477393514_0" pos="52.47" parking="0" started="1728.00" ended="1758.00" busStop="9932608366" initialPersons="0" loadedPersons="0" unloadedPersons="0" initialContainers="0" loadedContainers="0" unloadedContainers="0"/>
    <stopinfo id="22_bus_831:1" type="pt_bus" lane="-346673260#3_0" pos="140.69" parking="0" started="1744.00" ended="1774.00" busStop="-8886461645" initialPersons="0" loadedPersons="0" unloadedPersons="0" initialContainers="0" loadedContainers="0" unloadedContainers="0"/>
    <stopinfo id="15_bus_850:0" type="pt_bus" lane="-1098862378#1_0" pos="14.98" parking="0" started="1745.00" ended="1775.00" busStop="-8551460894" initialPersons="0" loadedPersons="0" unloadedPersons="0" initialContainers="0" loadedContainers="0" unloadedContainers="0"/>
    <stopinfo id="0_bus_UVX:0" type="pt_bus" lane="884914055#16_0" pos="38.08" parking="0" started="1745.00" ended="1775.00" busStop="9932608386" initialPersons="0" loadedPersons="0" unloadedPersons="0" initialContainers="0" loadedContainers="0" unloadedContainers="0"/>
    <stopinfo id="17_bus_862:1" type="pt_bus" lane="45877229#1_0" pos="18.38" parking="0" started="1756.00" ended="1786.00" busStop="9105707076" initialPersons="0" loadedPersons="0" unloadedPersons="0" initialContainers="0" loadedContainers="0" unloadedContainers="0"/>
    <stopinfo id="1_bus_UVX:1" type="pt_bus" lane="1001848377#4_0" pos="118.50" parking="0" started="1767.00" ended="1797.00" busStop="9246817713" initialPersons="0" loadedPersons="0" unloadedPersons="0" initialContainers="0" loadedContainers="0" unloadedContainers="0"/>
    <stopinfo id="15_bus_850:0" type="pt_bus" lane="1103204110#2_0" pos="15.35" parking="0" started="1803.00" ended="1833.00" busStop="9105907551" initialPersons="0" loadedPersons="0" unloadedPersons="0" initialContainers="0" loadedContainers="0" unloadedContainers="0"/>
    <stopinfo id="27_bus_805:1" type="pt_bus" lane="-117922059#12_0" pos="15.00" parking="0" started="1835.00" ended="1865.00" busStop="-9105784640" initialPersons="0" loadedPersons="0" unloadedPersons="0" initialContainers="0" loadedContainers="0" unloadedContainers="0"/>
    <stopinfo id="21_bus_833:0" type="pt_bus" lane="1225108307#8_0" pos="14.98" parking="0" started="1839.00" ended="1869.00" busStop="8542953439" initialPersons="0" loadedPersons="0" unloadedPersons="0" initialContainers="0" loadedContainers="0" unloadedContainers="0"/>
    <stopinfo id="22_bus_831:1" type="pt_bus" lane="1030777448#3_0" pos="22.05" parking="0" started="1859.00" ended="1889.00" busStop="8577294255" initialPersons="0" loadedPersons="0" unloadedPersons="0" initialContainers="0" loadedContainers="0" unloadedContainers="0"/>
    <stopinfo id="15_bus_850:0" type="pt_bus" lane="-1103204105#3_0" pos="18.78" parking="0" started="1878.00" ended="1908.00" busStop="-9124947647" initialPersons="0" loadedPersons="0" unloadedPersons="0" initialContainers="0" loadedContainers="0" unloadedContainers="0"/>
    <stopinfo id="2_bus_831:0" type="pt_bus" lane="10246981#0_0" pos="53.33" parking="0" started="1890.00" ended="1920.00" busStop="6343896649" initialPersons="0" loadedPersons="0" unloadedPersons="0" initialContainers="0" loadedContainers="0" unloadedContainers="0"/>
    <stopinfo id="16_bus_850:1" type="pt_bus" lane="1224483160_0" pos="101.70" parking="0" started="1917.00" ended="1947.00" busStop="9932513543" initialPersons="0" loadedPersons="0" unloadedPersons="0" initialContainers="0" loadedContainers="0" unloadedContainers="0"/>
    <stopinfo id="4_bus_805:0" type="pt_bus" lane="1225107993#1_0" pos="24.38" parking="0" started="1931.00" ended="1961.00" busStop="5388433609" initialPersons="0" loadedPersons="0" unloadedPersons="0" initialContainers="0" loadedContainers="0" unloadedContainers="0"/>
    <stopinfo id="25_train_750:1" type="pt_train" lane="626822759_0" pos="602.51" parking="0" started="1936.00" ended="1966.00" busStop="3017998930" initialPersons="0" loadedPersons="0" unloadedPersons="0" initialContainers="0" loadedContainers="0" unloadedContainers="0"/>
    <stopinfo id="17_bus_862:1" type="pt_bus" lane="44740447#0_0" pos="134.72" parking="0" started="1937.00" ended="1967.00" busStop="8544780328" initialPersons="0" loadedPersons="0" unloadedPersons="0" initialContainers="0" loadedContainers="0" unloadedContainers="0"/>
    <stopinfo id="0_bus_UVX:0" type="pt_bus" lane="1001839221_0" pos="44.12" parking="0" started="1942.00" ended="1972.00" busStop="9932608390" initialPersons="0" loadedPersons="0" unloadedPersons="0" initialContainers="0" loadedContainers="0" unloadedContainers="0"/>
    <stopinfo id="15_bus_850:0" type="pt_bus" lane="634114932#1_0" pos="23.24" parking="0" started="1947.00" ended="1977.00" busStop="8542450930" initialPersons="0" loadedPersons="0" unloadedPersons="0" initialContainers="0" loadedContainers="0" unloadedContainers="0"/>
    <stopinfo id="1_bus_UVX:1" type="pt_bus" lane="1037188591#2_0" pos="22.95" parking="0" started="1965.00" ended="1995.00" busStop="6343896643" initialPersons="0" loadedPersons="0" unloadedPersons="0" initialContainers="0" loadedContainers="0" unloadedContainers="0"/>
    <stopinfo id="30_bus_821:1" type="pt_bus" lane="-933030940_0" pos="22.22" parking="0" started="2016.00" ended="2046.00" busStop="-8542612061" initialPersons="0" loadedPersons="0" unloadedPersons="0" initialContainers="0" loadedContainers="0" unloadedContainers="0"/>
    <stopinfo id="21_bus_833:0" type="pt_bus" lane="228562182#6_0" pos="10.85" parking="0" started="2020.00" ended="2050.00" busStop="9118790712" initialPersons="0" loadedPersons="0" unloadedPersons="0" initialContainers="0" loadedContainers="0" unloadedContainers="0"/>
    <stopinfo id="17_bus_862:1" type="pt_bus" lane="568219148#5_0" pos="23.00" parking="0" started="2055.00" ended="2085.00" busStop="8672268996" initialPersons="0" loadedPersons="0" unloadedPersons="0" initialContainers="0" loadedContainers="0" unloadedContainers="0"/>
    <stopinfo id="1_bus_UVX:1" type="pt_bus" lane="1037188591#9_0" pos="33.77" parking="0" started="2081.00" ended="2111.00" busStop="9932608369" initialPersons="0" loadedPersons="0" unloadedPersons="0" initialContainers="0" loadedContainers="0" unloadedContainers="0"/>
    <stopinfo id="15_bus_850:0" type="pt_bus" lane="684673675#6_0" pos="33.69" parking="0" started="2103.00" ended="2133.00" busStop="8584734435" initialPersons="0" loadedPersons="0" unloadedPersons="0" initialContainers="0" loadedContainers="0" unloadedContainers="0"/>
    <stopinfo id="4_bus_805:0" type="pt_bus" lane="-117922059#4_0" pos="30.30" parking="0" started="2104.00" ended="2134.00" busStop="-9138268649" initialPersons="0" loadedPersons="0" unloadedPersons="0" initialContainers="0" loadedContainers="0" unloadedContainers="0"/>
    <stopinfo id="17_bus_862:1" type="pt_bus" lane="568219148#12_0" pos="21.51" parking="0" started="2114.00" ended="2144.00" busStop="8552063733" initialPersons="0" loadedPersons="0" unloadedPersons="0" initialContainers="0" loadedContainers="0" unloadedContainers="0"/>
    <stopinfo id="0_bus_UVX:0" type="pt_bus" lane="1001839223#6_0" pos="332.22" parking="0" started="2117.00" ended="2147.00" busStop="9932608387" initialPersons="0" loadedPersons="0" unloadedPersons="0" initialContainers="0" loadedContainers="0" unloadedContainers="0"/>
    <stopinfo id="21_bus_833:0" type="pt_bus" lane="228562182#3_0" pos="100.38" parking="0" started="2154.00" ended="2184.00" busStop="8873767502" initialPersons="0" loadedPersons="0" unloadedPersons="0" initialContainers="0" loadedContainers="0" unloadedContainers="0"/>
    <stopinfo id="17_bus_862:1" type="pt_bus" lane="568219148#15_0" pos="38.87" parking="0" started="2168.00" ended="2198.00" busStop="957807876" initialPersons="0" loadedPersons="0" unloadedPersons="0" initialContainers="0" loadedContainers="0" unloadedContainers="0"/>
    <stopinfo id="1_bus_UVX:1" type="pt_bus" lane="1028565369#1_0" pos="37.82" parking="0" started="2200.00" ended="2230.00" busStop="9932608372" initialPersons="0" loadedPersons="0" unloadedPersons="0" initialContainers="0" loadedContainers="0" unloadedContainers="0"/>
    <stopinfo id="17_bus_862:1" type="pt_bus" lane="568219148#18_0" pos="26.68" parking="0" started="2224.00" ended="2254.00" busStop="957807879" initialPersons="0" loadedPersons="0" unloadedPersons="0" initialContainers="0" loadedContainers="0" unloadedContainers="0"/>
    <stopinfo id="4_bus_805:0" type="pt_bus" lane="-117922059#12_0" pos="14.97" parking="0" started="2249.00" ended="2279.00" busStop="-9105784640" initialPersons="0" loadedPersons="0" unloadedPersons="0" initialContainers="0" loadedContainers="0" unloadedContainers="0"/>
    <stopinfo id="22_bus_831:1" type="pt_bus" lane="229097623#7_0" pos="13.28" parking="0" started="2258.00" ended="2288.00" busStop="9103852060" initialPersons="0" loadedPersons="0" unloadedPersons="0" initialContainers="0" loadedContainers="0" unloadedContainers="0"/>
    <stopinfo id="25_train_750:1" type="pt_train" lane="762329397_0" pos="550.88" parking="0" started="2272.00" ended="2302.00" busStop="3018001470" initialPersons="0" loadedPersons="0" unloadedPersons="0" initialContainers="0" loadedContainers="0" unloadedContainers="0"/>
    <stopinfo id="17_bus_862:1" type="pt_bus" lane="568219148#24_0" pos="25.13" parking="0" started="2284.00" ended="2314.00" busStop="2400947976" initialPersons="0" loadedPersons="0" unloadedPersons="0" initialContainers="0" loadedContainers="0" unloadedContainers="0"/>
    <stopinfo id="15_bus_850:0" type="pt_bus" lane="-231243108#9_0" pos="19.91" parking="0" started="2285.00" ended="2315.00" busStop="-11493019589" initialPersons="0" loadedPersons="0" unloadedPersons="0" initialContainers="0" loadedContainers="0" unloadedContainers="0"/>
    <stopinfo id="0_bus_UVX:0" type="pt_bus" lane="477393511_0" pos="127.29" parking="0" started="2316.00" ended="2346.00" busStop="9932608367" initialPersons="0" loadedPersons="0" unloadedPersons="0" initialContainers="0" loadedContainers="0" unloadedContainers="0"/>
    <stopinfo id="1_bus_UVX:1" type="pt_bus" lane="1028565369#8_0" pos="103.39" parking="0" started="2343.00" ended="2373.00" busStop="9139177656" initialPersons="0" loadedPersons="0" unloadedPersons="0" initialContainers="0" loadedContainers="0" unloadedContainers="0"/>
    <stopinfo id="15_bus_850:0" type="pt_bus" lane="-599894822#0_0" pos="31.81" parking="0" started="2349.00" ended="2379.00" busStop="-8568368617" initialPersons="0" loadedPersons="0" unloadedPersons="0" initialContainers="0" loadedContainers="0" unloadedContainers="0"/>
    <stopinfo id="17_bus_862:1" type="pt_bus" lane="-36872255#0_0" pos="19.48" parking="0" started="2353.00" ended="2383.00" busStop="-366399825" initialPersons="0" loadedPersons="0" unloadedPersons="0" initialContainers="0" loadedContainers="0" unloadedContainers="0"/>
    <stopinfo id="15_bus_850:0" type="pt_bus" lane="909694983_0" pos="35.45" parking="0" started="2401.00" ended="2431.00" busStop="8568366820" initialPersons="0" loadedPersons="0" unloadedPersons="0" initialContainers="0" loadedContainers="0" unloadedContainers="0"/>
    <stopinfo id="21_bus_833:0" type="pt_bus" lane="-10231591#3_0" pos="19.46" parking="0" started="2421.00" ended="2451.00" busStop="-8928589371" initialPersons="0" loadedPersons="0" unloadedPersons="0" initialContainers="0" loadedContainers="0" unloadedContainers="0"/>
    <stopinfo id="17_bus_862:1" type="pt_bus" lane="-600788076#7_0" pos="68.24" parking="0" started="2434.00" ended="2464.00" busStop="-366466391" initialPersons="0" loadedPersons="0" unloadedPersons="0" initialContainers="0" loadedContainers="0" unloadedContainers="0"/>
    <stopinfo id="22_bus_831:1" type="pt_bus" lane="477393514_0" pos="52.46" parking="0" started="2483.00" ended="2513.00" busStop="9932608366" initialPersons="0" loadedPersons="0" unloadedPersons="0" initialContainers="0" loadedContainers="0" unloadedContainers="0"/>
    <stopinfo id="29_bus_822:1" type="pt_bus" lane="477393511_0" pos="127.26" parking="0" started="2485.00" ended="2515.00" busStop="9932608367" initialPersons="0" loadedPersons="0" unloadedPersons="0" initialContainers="0" loadedContainers="0" unloadedContainers="0"/>
    <stopinfo id="17_bus_862:1" type="pt_bus" lane="-600788076#0_0" pos="42.42" parking="0" started="2501.00" ended="2531.00" busStop="-2400947965" initialPersons="0" loadedPersons="0" unloadedPersons="0" initialContainers="0" loadedContainers="0" unloadedContainers="0"/>
    <stopinfo id="27_bus_805:1" type="pt_bus" lane="-1037870374#1_0" pos="20.39" parking="0" started="2539.00" ended="2569.00" busStop="-8552049555" initialPersons="0" loadedPersons="0" unloadedPersons="0" initialContainers="0" loadedContainers="0" unloadedContainers="0"/>
    <stopinfo id="21_bus_833:0" type="pt_bus" lane="-10241562#1_0" pos="74.82" parking="0" started="2541.00" ended="2571.00" busStop="-8895668641" initialPersons="0" loadedPersons="0" unloadedPersons="0" initialContainers="0" loadedContainers="0" unloadedContainers="0"/>
    <stopinfo id="0_bus_UVX:0" type="pt_bus" lane="1225221152#1_0" pos="42.70" parking="0" started="2542.00" ended="2572.00" busStop="9932488270" initialPersons="0" loadedPersons="0" unloadedPersons="0" initialContainers="0" loadedContainers="0" unloadedContainers="0"/>
    <stopinfo id="17_bus_862:1" type="pt_bus" lane="600788021#1_0" pos="57.51" parking="0" started="2560.00" ended="2590.00" busStop="8925324470" initialPersons="0" loadedPersons="0" unloadedPersons="0" initialContainers="0" loadedContainers="0" unloadedContainers="0"/>
    <stopinfo id="15_bus_850:0" type="pt_bus" lane="-1103213888#0_0" pos="16.58" parking="0" started="2583.00" ended="2613.00" busStop="-8576337203" initialPersons="0" loadedPersons="0" unloadedPersons="0" initialContainers="0" loadedContainers="0" unloadedContainers="0"/>
    <stopinfo id="1_bus_UVX:1" type="pt_bus" lane="1225107993#1_0" pos="16.87" parking="0" started="2583.00" ended="2613.00" busStop="9932513538" initialPersons="0" loadedPersons="0" unloadedPersons="0" initialContainers="0" loadedContainers="0" unloadedContainers="0"/>
    <stopinfo id="22_bus_831:1" type="pt_bus" lane="-346646696#0_0" pos="28.08" parking="0" started="2607.00" ended="2637.00" busStop="-8542423137" initialPersons="0" loadedPersons="0" unloadedPersons="0" initialContainers="0" loadedContainers="0" unloadedContainers="0"/>
    <stopinfo id="30_bus_821:1" type="pt_bus" lane="-244437926#0_0" pos="43.28" parking="0" started="2621.00" ended="2651.00" busStop="-11361052134" initialPersons="0" loadedPersons="0" unloadedPersons="0" initialContainers="0" loadedContainers="0" unloadedContainers="0"/>
    <stopinfo id="17_bus_862:1" type="pt_bus" lane="-10234805#11_0" pos="22.09" parking="0" started="2647.00" ended="2677.00" busStop="-9103784641" initialPersons="0" loadedPersons="0" unloadedPersons="0" initialContainers="0" loadedContainers="0" unloadedContainers="0"/>
    <stopinfo id="15_bus_850:0" type="pt_bus" lane="-919107643#15_0" pos="54.69" parking="0" started="2650.00" ended="2680.00" busStop="-9105689127" initialPersons="0" loadedPersons="0" unloadedPersons="0" initialContainers="0" loadedContainers="0" unloadedContainers="0"/>
    <stopinfo id="2_bus_831:0" type="pt_bus" lane="1224483160_0" pos="64.60" parking="0" started="2670.00" ended="2700.00" busStop="2396515835" initialPersons="0" loadedPersons="0" unloadedPersons="0" initialContainers="0" loadedContainers="0" unloadedContainers="0"/>
    <stopinfo id="21_bus_833:0" type="pt_bus" lane="60747906#7_0" pos="64.08" parking="0" started="2697.00" ended="2727.00" busStop="9123329901" initialPersons="0" loadedPersons="0" unloadedPersons="0" initialContainers="0" loadedContainers="0" unloadedContainers="0"/>
    <stopinfo id="17_bus_862:1" type="pt_bus" lane="-10234805#1_0" pos="42.88" parking="0" started="2715.00" ended="2745.00" busStop="-8670297239" initialPersons="0" loadedPersons="0" unloadedPersons="0" initialContainers="0" loadedContainers="0" unloadedContainers="0"/>
    <stopinfo id="15_bus_850:0" type="pt_bus" lane="-1103213882#1_0" pos="21.73" parking="0" started="2769.00" ended="2799.00" busStop="-8869911047" initialPersons="0" loadedPersons="0" unloadedPersons="0" initialContainers="0" loadedContainers="0" unloadedContainers="0"/>
    <stopinfo id="21_bus_833:0" type="pt_bus" lane="60747906#5_0" pos="23.81" parking="0" started="2779.00" ended="2809.00" busStop="9128290350" initialPersons="0" loadedPersons="0" unloadedPersons="0" initialContainers="0" loadedContainers="0" unloadedContainers="0"/>
    <stopinfo id="17_bus_862:1" type="pt_bus" lane="10235902#8_0" pos="21.10" parking="0" started="2790.00" ended="2820.00" busStop="9138270623" initialPersons="0" loadedPersons="0" unloadedPersons="0" initialContainers="0" loadedContainers="0" unloadedContainers="0"/>
    <stopinfo id="15_bus_850:0" type="pt_bus" lane="-1352267895#0_0" pos="24.95" parking="0" started="2838.00" ended="2868.00" busStop="-9103807968" initialPersons="0" loadedPersons="0" unloadedPersons="0" initialContainers="0" loadedContainers="0" unloadedContainers="0"/>
    <stopinfo id="17_bus_862:1" type="pt_bus" lane="10235902#15_0" pos="63.96" parking="0" started="2871.00" ended="2901.00" busStop="9124927231" initialPersons="0" loadedPersons="0" unloadedPersons="0" initialContainers="0" loadedContainers="0" unloadedContainers="0"/>
    <stopinfo id="4_bus_805:0" type="pt_bus" lane="477393514_0" pos="52.47" parking="0" started="2884.00" ended="2914.00" busStop="9932608366" initialPersons="0" loadedPersons="0" unloadedPersons="0" initialContainers="0" loadedContainers="0" unloadedContainers="0"/>
    <stopinfo id="15_bus_850:0" type="pt_bus" lane="-1352100039_0" pos="15.00" parking="0" started="2894.00" ended="2924.00" busStop="-8849261098" initialPersons="0" loadedPersons="0" unloadedPersons="0" initialContainers="0" loadedContainers="0" unloadedContainers="0"/>
    <stopinfo id="17_bus_862:1" type="pt_bus" lane="10235902#18_0" pos="14.98" parking="0" started="2929.00" ended="2959.00" busStop="8584721658" initialPersons="0" loadedPersons="0" unloadedPersons="0" initialContainers="0" loadedContainers="0" unloadedContainers="0"/>
    <stopinfo id="21_bus_833:0" type="pt_bus" lane="684673673#1_0" pos="112.81" parking="0" started="2932.00" ended="2962.00" busStop="9932513540" initialPersons="0" loadedPersons="0" unloadedPersons="0" initialContainers="0" loadedContainers="0" unloadedContainers="0"/>
    <stopinfo id="22_bus_831:1" type="pt_bus" lane="1225221152#1_0" pos="24.92" parking="0" started="2966.00" ended="2996.00" busStop="9932488271" initialPersons="0" loadedPersons="0" unloadedPersons="0" initialContainers="0" loadedContainers="0" unloadedContainers="0"/>
    <stopinfo id="15_bus_850:0" type="pt_bus" lane="1098897323#1_0" pos="23.78" parking="0" started="2981.00" ended="3011.00" busStop="8572449564" initialPersons="0" loadedPersons="0" unloadedPersons="0" initialContainers="0" loadedContainers="0" unloadedContainers="0"/>
    <stopinfo id="17_bus_862:1" type="pt_bus" lane="10235902#20_0" pos="112.35" parking="0" started="2986.00" ended="3016.00" busStop="9105748140" initialPersons="0" loadedPersons="0" unloadedPersons="0" initialContainers="0" loadedContainers="0" unloadedContainers="0"/>
    <stopinfo id="15_bus_850:0" type="pt_bus" lane="-842663974#12_0" pos="38.80" parking="0" started="3051.00" ended="3081.00" busStop="-9124305657" initialPersons="0" loadedPersons="0" unloadedPersons="0" initialContainers="0" loadedContainers="0" unloadedContainers="0"/>
    <stopinfo id="17_bus_862:1" type="pt_bus" lane="-231247767_0" pos="67.18" parking="0" started="3077.00" ended="3107.00" busStop="-8783782792" initialPersons="0" loadedPersons="0" unloadedPersons="0" initialContainers="0" loadedContainers="0" unloadedContainers="0"/>
    <stopinfo id="15_bus_850:0" type="pt_bus" lane="-1103213876#2_0" pos="21.54" parking="0" started="3139.00" ended="3169.00" busStop="-9124890027" initialPersons="0" loadedPersons="0" unloadedPersons="0" initialContainers="0" loadedContainers="0" unloadedContainers="0"/>
    <stopinfo id="17_bus_862:1" type="pt_bus" lane="-10231865#1_0" pos="21.57" parking="0" started="3149.00" ended="3179.00" busStop="-8544564429" initialPersons="0" loadedPersons="0" unloadedPersons="0" initialContainers="0" loadedContainers="0" unloadedContainers="0"/>
    <stopinfo id="15_bus_850:0" type="pt_bus" lane="-10237317#8_0" pos="19.96" parking="0" started="3206.00" ended="3236.00" busStop="-9123291378" initialPersons="0" loadedPersons="0" unloadedPersons="0" initialContainers="0" loadedContainers="0" unloadedContainers="0"/>
    <stopinfo id="17_bus_862:1" type="pt_bus" lane="-684690130#6_0" pos="27.44" parking="0" started="3262.00" ended="3292.00" busStop="-8849388476" initialPersons="0" loadedPersons="0" unloadedPersons="0" initialContainers="0" loadedContainers="0" unloadedContainers="0"/>
    <stopinfo id="15_bus_850:0" type="pt_bus" lane="1103213873#1_0" pos="14.99" parking="0" started="3303.00" ended="3333.00" busStop="8551528604" initialPersons="0" loadedPersons="0" unloadedPersons="0" initialContainers="0" loadedContainers="0" unloadedContainers="0"/>
    <stopinfo id="27_bus_805:1" type="pt_bus" lane="1225096172#3_0" pos="35.19" parking="0" started="3337.00" ended="3367.00" busStop="8584737276" initialPersons="0" loadedPersons="0" unloadedPersons="0" initialContainers="0" loadedContainers="0" unloadedContainers="0"/>
    <stopinfo id="17_bus_862:1" type="pt_bus" lane="-10236172#39_0" pos="58.31" parking="0" started="3362.00" ended="3392.00" busStop="-8568349646" initialPersons="0" loadedPersons="0" unloadedPersons="0" initialContainers="0" loadedContainers="0" unloadedContainers="0"/>
    <stopinfo id="15_bus_850:0" type="pt_bus" lane="1103213873#19_0" pos="24.00" parking="0" started="3372.00" ended="3402.00" busStop="8572464565" initialPersons="0" loadedPersons="0" unloadedPersons="0" initialContainers="0" loadedContainers="0" unloadedContainers="0"/>
    <stopinfo id="17_bus_862:1" type="pt_bus" lane="-10236172#33_0" pos="37.54" parking="0" started="3429.00" ended="3459.00" busStop="-8544805026" initialPersons="0" loadedPersons="0" unloadedPersons="0" initialContainers="0" loadedContainers="0" unloadedContainers="0"/>
    <stopinfo id="15_bus_850:0" type="pt_bus" lane="229715468#0_0" pos="14.99" parking="0" started="3455.00" ended="3485.00" busStop="8849397578" initialPersons="0" loadedPersons="0" unloadedPersons="0" initialContainers="0" loadedContainers="0" unloadedContainers="0"/>
    <stopinfo id="17_bus_862:1" type="pt_bus" lane="-10236172#27_0" pos="32.31" parking="0" started="3497.00" ended="3527.00" busStop="-8927889017" initialPersons="0" loadedPersons="0" unloadedPersons="0" initialContainers="0" loadedContainers="0" unloadedContainers="0"/>
    <stopinfo id="15_bus_850:0" type="pt_bus" lane="229715468#10_0" pos="23.69" parking="0" started="3514.00" ended="3544.00" busStop="4145236921" initialPersons="0" loadedPersons="0" unloadedPersons="0" initialContainers="0" loadedContainers="0" unloadedContainers="0"/>
    <stopinfo id="15_bus_850:0" type="pt_bus" lane="634107308#3_0" pos="19.18" parking="0" started="3588.00" ended="3618.00" busStop="4145236918" initialPersons="0" loadedPersons="0" unloadedPersons="0" initialContainers="0" loadedContainers="0" unloadedContainers="0"/>
    <stopinfo id="17_bus_862:1" type="pt_bus" lane="10232468#2_0" pos="14.98" parking="0" started="3615.00" ended="3645.00" busStop="8551512663" initialPersons="0" loadedPersons="0" unloadedPersons="0" initialContainers="0" loadedContainers="0" unloadedContainers="0"/>
    <stopinfo id="15_bus_850:0" type="pt_bus" lane="-634107312#1_0" pos="14.99" parking="0" started="3658.00" ended="3688.00" busStop="-9118813792" initialPersons="0" loadedPersons="0" unloadedPersons="0" initialContainers="0" loadedContainers="0" unloadedContainers="0"/>
    <stopinfo id="17_bus_862:1" type="pt_bus" lane="10232468#7_0" pos="14.98" parking="0" started="3680.00" ended="3710.00" busStop="5705821980" initialPersons="0" loadedPersons="0" unloadedPersons="0" initialContainers="0" loadedContainers="0" unloadedContainers="0"/>
    <stopinfo id="15_bus_850:0" type="pt_bus" lane="1103526540#3_0" pos="29.49" parking="0" started="3716.00" ended="3746.00" busStop="9118072814" initialPersons="0" loadedPersons="0" unloadedPersons="0" initialContainers="0" loadedContainers="0" unloadedContainers="0"/>
    <stopinfo id="17_bus_862:1" type="pt_bus" lane="599894831#0_0" pos="20.58" parking="0" started="3754.00" ended="3784.00" busStop="8577294457" initialPersons="0" loadedPersons="0" unloadedPersons="0" initialContainers="0" loadedContainers="0" unloadedContainers="0"/>
    <stopinfo id="15_bus_850:0" type="pt_bus" lane="-119006869#6_0" pos="54.85" parking="0" started="3806.00" ended="3836.00" busStop="-8544571432" initialPersons="0" loadedPersons="0" unloadedPersons="0" initialContainers="0" loadedContainers="0" unloadedContainers="0"/>
    <stopinfo id="17_bus_862:1" type="pt_bus" lane="599894831#7_0" pos="15.00" parking="0" started="3820.00" ended="3850.00" busStop="5705821974" initialPersons="0" loadedPersons="0" unloadedPersons="0" initialContainers="0" loadedContainers="0" unloadedContainers="0"/>
    <stopinfo id="15_bus_850:0" type="pt_bus" lane="10237320#1_0" pos="14.99" parking="0" started="3874.00" ended="3904.00" busStop="8779083155" initialPersons="0" loadedPersons="0" unloadedPersons="0" initialContainers="0" loadedContainers="0" unloadedContainers="0"/>
    <stopinfo id="17_bus_862:1" type="pt_bus" lane="599894825#1_0" pos="17.72" parking="0" started="3928.00" ended="3958.00" busStop="9105741116" initialPersons="0" loadedPersons="0" unloadedPersons="0" initialContainers="0" loadedContainers="0" unloadedContainers="0"/>
    <stopinfo id="15_bus_850:0" type="pt_bus" lane="10237320#10_0" pos="84.69" parking="0" started="3938.00" ended="3968.00" busStop="8604568108" initialPersons="0" loadedPersons="0" unloadedPersons="0" initialContainers="0" loadedContainers="0" unloadedContainers="0"/>
    <stopinfo id="17_bus_862:1" type="pt_bus" lane="231243108#1_0" pos="49.11" parking="0" started="3991.00" ended="4021.00" busStop="8552058928" initialPersons="0" loadedPersons="0" unloadedPersons="0" initialContainers="0" loadedContainers="0" unloadedContainers="0"/>
    <stopinfo id="15_bus_850:0" type="pt_bus" lane="1103526533#2_0" pos="24.58" parking="0" started="3995.00" ended="4025.00" busStop="8990574492" initialPersons="0" loadedPersons="0" unloadedPersons="0" initialContainers="0" loadedContainers="0" unloadedContainers="0"/>
    <stopinfo id="17_bus_862:1" type="pt_bus" lane="231243108#8_0" pos="22.33" parking="0" started="4047.00" ended="4077.00" busStop="8544530509" initialPersons="0" loadedPersons="0" unloadedPersons="0" initialContainers="0" loadedContainers="0" unloadedContainers="0"/>
    <stopinfo id="15_bus_850:0" type="pt_bus" lane="1103526530#1_0" pos="37.06" parking="0" started="4064.00" ended="4094.00" busStop="9138293030" initialPersons="0" loadedPersons="0" unloadedPersons="0" initialContainers="0" loadedContainers="0" unloadedContainers="0"/>
    <stopinfo id="15_bus_850:0" type="pt_bus" lane="1103526528#2_0" pos="14.32" parking="0" started="4176.00" ended="4206.00" busStop="9124266271" initialPersons="0" loadedPersons="0" unloadedPersons="0" initialContainers="0" loadedContainers="0" unloadedContainers="0"/>
    <stopinfo id="17_bus_862:1" type="pt_bus" lane="776681829#5_0" pos="99.15" parking="0" started="4211.00" ended="4241.00" busStop="6863882459" initialPersons="0" loadedPersons="0" unloadedPersons="0" initialContainers="0" loadedContainers="0" unloadedContainers="0"/>
    <stopinfo id="15_bus_850:0" type="pt_bus" lane="-810638655#1_0" pos="22.69" parking="0" started="4281.00" ended="4311.00" busStop="-8552050219" initialPersons="0" loadedPersons="0" unloadedPersons="0" initialContainers="0" loadedContainers="0" unloadedContainers="0"/>
    <stopinfo id="15_bus_850:0" type="pt_bus" lane="-119006773#3_0" pos="62.42" parking="0" started="4340.00" ended="4370.00" busStop="-8870062512" initialPersons="0" loadedPersons="0" unloadedPersons="0" initialContainers="0" loadedContainers="0" unloadedContainers="0"/>
    <stopinfo id="15_bus_850:0" type="pt_bus" lane="-79800401#7_0" pos="14.98" parking="0" started="4447.00" ended="4477.00" busStop="-8927894153" initialPersons="0" loadedPersons="0" unloadedPersons="0" initialContainers="0" loadedContainers="0" unloadedContainers="0"/>
    <stopinfo id="15_bus_850:0" type="pt_bus" lane="-684661233#0_0" pos="14.98" parking="0" started="4572.00" ended="4602.00" busStop="-8877986508" initialPersons="0" loadedPersons="0" unloadedPersons="0" initialContainers="0" loadedContainers="0" unloadedContainers="0"/>
    <stopinfo id="15_bus_850:0" type="pt_bus" lane="10248479#1_0" pos="73.92" parking="0" started="4622.00" ended="4652.00" busStop="8544849774" initialPersons="0" loadedPersons="0" unloadedPersons="0" initialContainers="0" loadedContainers="0" unloadedContainers="0"/>
    <stopinfo id="15_bus_850:0" type="pt_bus" lane="10233792#1_0" pos="57.23" parking="0" started="4677.00" ended="4707.00" busStop="8552052405" initialPersons="0" loadedPersons="0" unloadedPersons="0" initialContainers="0" loadedContainers="0" unloadedContainers="0"/>
    <stopinfo id="15_bus_850:0" type="pt_bus" lane="227602198#4_0" pos="20.97" parking="0" started="4737.00" ended="4767.00" busStop="8573408531" initialPersons="0" loadedPersons="0" unloadedPersons="0" initialContainers="0" loadedContainers="0" unloadedContainers="0"/>
    <stopinfo id="15_bus_850:0" type="pt_bus" lane="1225020250#1_0" pos="52.29" parking="0" started="4856.00" ended="4886.00" busStop="958983390" initialPersons="0" loadedPersons="0" unloadedPersons="0" initialContainers="0" loadedContainers="0" unloadedContainers="0"/>
    <stopinfo id="15_bus_850:0" type="pt_bus" lane="346410603#0_0" pos="37.43" parking="0" started="4938.00" ended="4968.00" busStop="2369125890" initialPersons="0" loadedPersons="0" unloadedPersons="0" initialContainers="0" loadedContainers="0" unloadedContainers="0"/>
    <stopinfo id="15_bus_850:0" type="pt_bus" lane="-231974869#14_0" pos="42.74" parking="0" started="5068.00" ended="5098.00" busStop="-9123357236" initialPersons="0" loadedPersons="0" unloadedPersons="0" initialContainers="0" loadedContainers="0" unloadedContainers="0"/>
    <stopinfo id="15_bus_850:0" type="pt_bus" lane="-231974869#9_0" pos="56.25" parking="0" started="5124.00" ended="5154.00" busStop="-3530035888" initialPersons="0" loadedPersons="0" unloadedPersons="0" initialContainers="0" loadedContainers="0" unloadedContainers="0"/>
    <stopinfo id="15_bus_850:0" type="pt_bus" lane="-231974869#0_0" pos="25.86" parking="0" started="5191.00" ended="5221.00" busStop="-959019624" initialPersons="0" loadedPersons="0" unloadedPersons="0" initialContainers="0" loadedContainers="0" unloadedContainers="0"/>
    <stopinfo id="15_bus_850:0" type="pt_bus" lane="-82362079#18_0" pos="35.31" parking="0" started="5259.00" ended="5289.00" busStop="-9138293064" initialPersons="0" loadedPersons="0" unloadedPersons="0" initialContainers="0" loadedContainers="0" unloadedContainers="0"/>
    <stopinfo id="15_bus_850:0" type="pt_bus" lane="-231764115#23_0" pos="9.96" parking="0" started="5360.00" ended="5390.00" busStop="-8886451184" initialPersons="0" loadedPersons="0" unloadedPersons="0" initialContainers="0" loadedContainers="0" unloadedContainers="0"/>
    <stopinfo id="15_bus_850:0" type="pt_bus" lane="-231764115#13_0" pos="9.42" parking="0" started="5414.00" ended="5444.00" busStop="-8542170799" initialPersons="0" loadedPersons="0" unloadedPersons="0" initialContainers="0" loadedContainers="0" unloadedContainers="0"/>
    <stopinfo id="15_bus_850:0" type="pt_bus" lane="-231764115#0_0" pos="12.64" parking="0" started="5491.00" ended="5521.00" busStop="-959058612" initialPersons="0" loadedPersons="0" unloadedPersons="0" initialContainers="0" loadedContainers="0" unloadedContainers="0"/>
    <stopinfo id="15_bus_850:0" type="pt_bus" lane="-1270449033#0_0" pos="14.98" parking="0" started="5585.00" ended="5615.00" busStop="-959058615" initialPersons="0" loadedPersons="0" unloadedPersons="0" initialContainers="0" loadedContainers="0" unloadedContainers="0"/>
    <stopinfo id="15_bus_850:0" type="pt_bus" lane="32878196#1_0" pos="26.35" parking="0" started="5651.00" ended="5681.00" busStop="8891356952" initialPersons="0" loadedPersons="0" unloadedPersons="0" initialContainers="0" loadedContainers="0" unloadedContainers="0"/>
    <stopinfo id="15_bus_850:0" type="pt_bus" lane="32878196#4_0" pos="51.77" parking="0" started="5705.00" ended="5735.00" busStop="959058587" initialPersons="0" loadedPersons="0" unloadedPersons="0" initialContainers="0" loadedContainers="0" unloadedContainers="0"/>
    <stopinfo id="15_bus_850:0" type="pt_bus" lane="32878196#13_0" pos="25.76" parking="0" started="5767.00" ended="5797.00" busStop="959058595" initialPersons="0" loadedPersons="0" unloadedPersons="0" initialContainers="0" loadedContainers="0" unloadedContainers="0"/>
    <stopinfo id="15_bus_850:0" type="pt_bus" lane="231241501#1_0" pos="35.25" parking="0" started="5838.00" ended="5868.00" busStop="8542449501" initialPersons="0" loadedPersons="0" unloadedPersons="0" initialContainers="0" loadedContainers="0" unloadedContainers="0"/>
    <stopinfo id="15_bus_850:0" type="pt_bus" lane="1353595025_0" pos="29.07" parking="0" started="5896.00" ended="5926.00" busStop="959058572" initialPersons="0" loadedPersons="0" unloadedPersons="0" initialContainers="0" loadedContainers="0" unloadedContainers="0"/>
    <stopinfo id="15_bus_850:0" type="pt_bus" lane="814302009#2_0" pos="26.36" parking="0" started="5984.00" ended="6014.00" busStop="9124296386" initialPersons="0" loadedPersons="0" unloadedPersons="0" initialContainers="0" loadedContainers="0" unloadedContainers="0"/>
    <stopinfo id="15_bus_850:0" type="pt_bus" lane="814302009#6_0" pos="29.57" parking="0" started="6039.00" ended="6069.00" busStop="9105787934" initialPersons="0" loadedPersons="0" unloadedPersons="0" initialContainers="0" loadedContainers="0" unloadedContainers="0"/>
    <stopinfo id="15_bus_850:0" type="pt_bus" lane="1188525201#1_0" pos="37.25" parking="0" started="6171.00" ended="6201.00" busStop="8544541138" initialPersons="0" loadedPersons="0" unloadedPersons="0" initialContainers="0" loadedContainers="0" unloadedContainers="0"/>
    <stopinfo id="15_bus_850:0" type="pt_bus" lane="1188525200#0_0" pos="44.74" parking="0" started="6235.00" ended="6265.00" busStop="8895668644" initialPersons="0" loadedPersons="0" unloadedPersons="0" initialContainers="0" loadedContainers="0" unloadedContainers="0"/>
    <stopinfo id="15_bus_850:0" type="pt_bus" lane="413241572#4_0" pos="252.77" parking="0" started="6304.00" ended="6334.00" busStop="9126599778" initialPersons="0" loadedPersons="0" unloadedPersons="0" initialContainers="0" loadedContainers="0" unloadedContainers="0"/>
    <stopinfo id="15_bus_850:0" type="pt_bus" lane="814301987#0_0" pos="24.68" parking="0" started="6371.00" ended="6401.00" busStop="8783796050" initialPersons="0" loadedPersons="0" unloadedPersons="0" initialContainers="0" loadedContainers="0" unloadedContainers="0"/>
    <stopinfo id="15_bus_850:0" type="pt_bus" lane="814301987#20_0" pos="14.99" parking="0" started="6456.00" ended="6486.00" busStop="9124273483" initialPersons="0" loadedPersons="0" unloadedPersons="0" initialContainers="0" loadedContainers="0" unloadedContainers="0"/>
    <stopinfo id="15_bus_850:0" type="pt_bus" lane="-172743649#38_0" pos="64.95" parking="0" started="6583.00" ended="6613.00" busStop="-8542125054" initialPersons="0" loadedPersons="0" unloadedPersons="0" initialContainers="0" loadedContainers="0" unloadedContainers="0"/>
    <stopinfo id="15_bus_850:0" type="pt_bus" lane="-172743649#34_0" pos="25.72" parking="0" started="6669.00" ended="6699.00" busStop="-9103863062" initialPersons="0" loadedPersons="0" unloadedPersons="0" initialContainers="0" loadedContainers="0" unloadedContainers="0"/>
    <stopinfo id="15_bus_850:0" type="pt_bus" lane="-172743649#23_0" pos="23.99" parking="0" started="6732.00" ended="6762.00" busStop="-8561087916" initialPersons="0" loadedPersons="0" unloadedPersons="0" initialContainers="0" loadedContainers="0" unloadedContainers="0"/>
    <stopinfo id="15_bus_850:0" type="pt_bus" lane="-172743649#0_0" pos="14.99" parking="0" started="6810.00" ended="6840.00" busStop="-8886479202" initialPersons="0" loadedPersons="0" unloadedPersons="0" initialContainers="0" loadedContainers="0" unloadedContainers="0"/>
    <stopinfo id="15_bus_850:0" type="pt_bus" lane="231366549#2_0" pos="79.05" parking="0" started="6982.00" ended="7012.00" busStop="8928578462" initialPersons="0" loadedPersons="0" unloadedPersons="0" initialContainers="0" loadedContainers="0" unloadedContainers="0"/>
    <stopinfo id="15_bus_850:0" type="pt_bus" lane="346479769#1_0" pos="25.92" parking="0" started="7077.00" ended="7107.00" busStop="8577326192" initialPersons="0" loadedPersons="0" unloadedPersons="0" initialContainers="0" loadedContainers="0" unloadedContainers="0"/>
    <stopinfo id="15_bus_850:0" type="pt_bus" lane="231250765_0" pos="82.41" parking="0" started="7204.00" ended="7234.00" busStop="11360306139" initialPersons="0" loadedPersons="0" unloadedPersons="0" initialContainers="0" loadedContainers="0" unloadedContainers="0"/>
</stops>
